funniest/__init__.py
funniest_dev_11_12_18-0.1.dist-info/METADATA
funniest_dev_11_12_18-0.1.dist-info/WHEEL
funniest_dev_11_12_18-0.1.dist-info/top_level.txt
funniest_dev_11_12_18-0.1.dist-info/RECORD
