Metadata-Version: 2.1
Name: funniest-dev-11-12-18
Version: 0.1
Summary: The funniest joke in the world
Home-page: UNKNOWN
Author: Flying Circus
Author-email: flyingcircus@example.com
License: MIT
Platform: UNKNOWN
